Metadata-Version: 1.1
Name: zerolog
Version: 0.3
Summary: Minimalist and agnostic log aggregation with zeromq from tcp
Home-page: https://github.com/TheGhouls/zerolog
Author: TheGhouls
Author-email: manu.valette@gmail.com
License: UNKNOWN
Keywords: logging,logs,zeromq,rsyslog
Platform: UNKNOWN
Classifier: License :: OSI Approved :: MIT License
Classifier: Programming Language :: Python :: 3.3
Classifier: Programming Language :: Python :: 3.4
Classifier: Programming Language :: Python :: 3.5
